<?xml version="1.0" encoding="UTF-8"?>
<objects serializationModel="Studio.02.00.00">
	<object class="AudioFile" id="{9081e760-8692-4bc2-8810-24a57bf12d3e}">
		<property name="assetPath">
			<value>Step 06.wav</value>
		</property>
		<property name="frequencyInKHz">
			<value>48</value>
		</property>
		<property name="channelCount">
			<value>1</value>
		</property>
		<property name="length">
			<value>0.37852083333333331</value>
		</property>
		<relationship name="masterAssetFolder">
			<destination>{1c9df0a9-0c12-4f60-b3bd-8bd9685e7594}</destination>
		</relationship>
	</object>
</objects>
